split_downloader/__init__.py
split_downloader/code.py
split_downloader_peta-0.1.3.dist-info/METADATA
split_downloader_peta-0.1.3.dist-info/WHEEL
split_downloader_peta-0.1.3.dist-info/entry_points.txt
split_downloader_peta-0.1.3.dist-info/top_level.txt
split_downloader_peta-0.1.3.dist-info/RECORD
