Metadata-Version: 2.1
Name: split-downloader-peta
Version: 0.1.3
Summary: A simple multi-threaded download manager
Author: Manoj Kumar Reddy Peta
Author-email: manojpeta30@gmail.com
Requires-Python: >=3.6
Requires-Dist: requests
Requires-Dist: tqdm
Requires-Dist: rich
